chaos_cases/__init__.py
chaos_cases/api.py
chaos_cases/main.py
chaos_cases-0.0.3.dist-info/LICENSE
chaos_cases-0.0.3.dist-info/METADATA
chaos_cases-0.0.3.dist-info/WHEEL
chaos_cases-0.0.3.dist-info/top_level.txt
chaos_cases-0.0.3.dist-info/RECORD
